MANIFEST.in
README.rst
pyproject.toml
setup.py
adapya/__init__.py
adapya/entirex/cmdinfo.py
adapya/entirex/__init__.py
adapya/entirex/acierror.py
adapya/entirex/broker.py
adapya/entirex/cmdinfo.py
adapya/entirex/etbcinf.py
adapya/entirex/etbcinf8.py
adapya/entirex/doc/conf.py
adapya_entirex.egg-info/PKG-INFO
adapya_entirex.egg-info/SOURCES.txt
adapya_entirex.egg-info/dependency_links.txt
adapya_entirex.egg-info/namespace_packages.txt
adapya_entirex.egg-info/not-zip-safe
adapya_entirex.egg-info/requires.txt
adapya_entirex.egg-info/top_level.txt