Metadata-Version: 1.1
Name: adapya-entirex
Version: 1.3.0
Summary: adapya-entirex - Persistent messaging with webMethods EntireX Broker
Home-page: https://github.com/SoftwareAG/adapya-entirex
Author: mmueller
Author-email: mm@softwareag.com
License: Apache License 2.0
Keywords: softwareag webMethods EntireX Broker messaging
Platform: any
Classifier: Development Status :: 5 - Production/Stable
Classifier: License :: OSI Approved :: Apache Software License
Classifier: Intended Audience :: Developers
Classifier: Natural Language :: English
Classifier: Operating System :: Microsoft :: Windows
Classifier: Operating System :: POSIX :: AIX
Classifier: Operating System :: POSIX :: HP-UX
Classifier: Operating System :: POSIX :: SunOS/Solaris
Classifier: Operating System :: POSIX :: Linux
Classifier: Programming Language :: Python
Classifier: Programming Language :: Python :: 2.7
Classifier: Programming Language :: Python :: 3.6
Classifier: Programming Language :: Python :: 3.7
Classifier: Programming Language :: Python :: 3.8
Classifier: Programming Language :: Python :: 3.9
Classifier: Programming Language :: Python :: 3.10
Classifier: Programming Language :: Python :: 3.11
Classifier: Programming Language :: Python :: 3.12
Classifier: Topic :: Software Development
